odoo8_addon_product_code_builder-8.0.0.0.1.99.dev25-py2.7-nspkg.pth
odoo8_addon_product_code_builder-8.0.0.0.1.99.dev25.dist-info/METADATA
odoo8_addon_product_code_builder-8.0.0.0.1.99.dev25.dist-info/RECORD
odoo8_addon_product_code_builder-8.0.0.0.1.99.dev25.dist-info/WHEEL
odoo8_addon_product_code_builder-8.0.0.0.1.99.dev25.dist-info/namespace_packages.txt
odoo8_addon_product_code_builder-8.0.0.0.1.99.dev25.dist-info/top_level.txt
odoo_addons/product_code_builder/README.rst
odoo_addons/product_code_builder/__init__.py
odoo_addons/product_code_builder/__openerp__.py
odoo_addons/product_code_builder/hooks.py
odoo_addons/product_code_builder/demo/product.attribute.csv
odoo_addons/product_code_builder/demo/product.attribute.value.csv
odoo_addons/product_code_builder/demo/product_demo.xml
odoo_addons/product_code_builder/i18n/ca.po
odoo_addons/product_code_builder/i18n/de.po
odoo_addons/product_code_builder/i18n/es.po
odoo_addons/product_code_builder/i18n/fr.po
odoo_addons/product_code_builder/i18n/it.po
odoo_addons/product_code_builder/i18n/product_code_builder.pot
odoo_addons/product_code_builder/i18n/sl.po
odoo_addons/product_code_builder/models/__init__.py
odoo_addons/product_code_builder/models/product.py
odoo_addons/product_code_builder/models/product_attribute.py
odoo_addons/product_code_builder/static/description/icon.png
odoo_addons/product_code_builder/static/description/img_0.png
odoo_addons/product_code_builder/static/description/img_1.png
odoo_addons/product_code_builder/static/description/img_2.png
odoo_addons/product_code_builder/tests/__init__.py
odoo_addons/product_code_builder/tests/test_code.py
odoo_addons/product_code_builder/views/product_attribute_view.xml
odoo_addons/product_code_builder/views/product_view.xml
